ttnmqtt/__init__.py
ttnmqtt/ttnmqtt.py
ttnmqtt-0.9.4.dist-info/DESCRIPTION.rst
ttnmqtt-0.9.4.dist-info/METADATA
ttnmqtt-0.9.4.dist-info/RECORD
ttnmqtt-0.9.4.dist-info/WHEEL
ttnmqtt-0.9.4.dist-info/metadata.json
ttnmqtt-0.9.4.dist-info/top_level.txt
