Metadata-Version: 1.0
Name: ttnmqtt
Version: 0.9.4
Summary: small package to make mqtt connection to ttn
Home-page: https://github.com/TheThingsNetwork/python-app-sdk
Author: Emmanuelle Lejeail
Author-email: manu.lejeail@gmail.com
License: MIT
Platform: UNKNOWN
